README.md
setup.cfg
setup.py
DiscordHooks/__init__.py
DiscordHooks/embed.py
DiscordHooks/hook.py
DiscordHooks.egg-info/PKG-INFO
DiscordHooks.egg-info/SOURCES.txt
DiscordHooks.egg-info/dependency_links.txt
DiscordHooks.egg-info/top_level.txt