Metadata-Version: 1.0
Name: DiscordHooks
Version: 1.0
Summary: A python module for easily execute discord webhooks with embeds and more.
Home-page: https://github.com/MeitarR/DiscordHooks
Author: MeitarR
Author-email: meitarr013@gmail.com
License: UNKNOWN
Platform: UNKNOWN
